Workbook

Sheet Daily Tracker
A1: Date | B1: Week | C1: Day | D1: Energy | E1: DSA Topic | F1: HLD Topic | G1: LLD Topic | H1: Action | I1: Time | J1: Problem Solved | K1: Solved Without Help | L1: Spoke Out Loud | M1: Mistake Logged | N1: Score 0-5
A2: 2026-08-25 | B2: 1 | C2: Tue | E2: Arrays + hashing (warm-up) | F2: — | G2: — | H2: Solve 1 easy/medium to start rhythm | I2: 45-60 min
A3: 2026-08-26 | B3: 1 | C3: Wed | E3: Two pointers (warm-up) | F3: — | G3: — | H3: Solve 1 two pointer problem | I3: 45-60 min
A4: 2026-08-27 | B4: 1 | C4: Thu | E4: Sliding window (warm-up) | F4: — | G4: — | H4: Solve 1 sliding window problem | I4: 45-60 min
A5: 2026-08-28 | B5: 1 | C5: Fri | E5: Binary search (warm-up) | F5: — | G5: — | H5: Solve 1 binary search problem | I5: 45-60 min
A6: 2026-08-29 | B6: 1 | C6: Sat | E6: DP: 1D easy (warm-up) | F6: — | G6: — | H6: Solve 1 easy DP (climbing stairs / fibonacci style) | I6: 45-60 min
A7: 2026-08-30 | B7: 1 | C7: Sun | E7: Graphs: BFS easy (warm-up) | F7: — | G7: — | H7: Solve 1 easy graph (flood fill / number of islands) | I7: 45-60 min
A8: 2026-08-31 | B8: 1 | C8: Mon | E8: Revision: weakest | F8: — | G8: — | H8: Re-solve 1 mistake; update tracker | I8: 45 min
A9: 2026-09-01 | B9: 2 | C9: Tue | E9: DP: 1D state transition (house robber, decode ways) | F9: SD template: requirements → APIs → data model → architecture → deep dive | G9: What is LLD? OOP basics: classes, objects, encapsulation, abstraction | H9: Solve 1 DP + learn SD template + read OOP | I9: 100 min
A10: 2026-09-02 | B10: 2 | C10: Wed | E10: DP: 1D subsequence (LIS, coin change, word break) | F10: Capacity estimation: users, QPS, storage math | G10: SOLID: Single Responsibility + Open-Closed | H10: Solve 1 DP + practice estimation + understand SRP/OCP | I10: 100 min
A11: 2026-09-03 | B11: 2 | C11: Thu | E11: DP: 2D grid (unique paths, min path sum) | F11: Database: SQL vs NoSQL, indexes, replication | G11: SOLID: Liskov + Interface Segregation + Dependency Inversion | H11: Solve 1 2D DP + note DB tradeoffs + complete SOLID | I11: 100 min
A12: 2026-09-04 | B12: 2 | C12: Fri | E12: Graphs: DFS + cycle detection | F12: Caching: read-aside, write-through, TTL, invalidation | G12: Design patterns: Strategy pattern (code it) | H12: 2 hrs. Solve 1 graph + diagram cache + code strategy | I12: 2 hrs
A13: 2026-09-05 | B13: 2 | C13: Sat | E13: Graphs: topological sort (course schedule) | F13: Message queues: async, pub-sub, Kafka basics | G13: Design patterns: Observer pattern (code it) | H13: Solve 1 topo sort + note queue use cases + code observer | I13: 2 hrs
... A43: 2026-10-05 | B43: 6 | C43: Mon | E43: Rest + light review | F43: Read HLD notes only | G43: Read LLD notes only | H43: No new problems. Trust prep. Rest. | I43: 1 hr

Sheet 6 Week Plan
A1: Week | B1: Theme | C1: Main Outcome | D1: Daily Load | E1: Non-negotiable | F1: End of Week Check
A2: 1 | B2: Lenient — build rhythm | C2: Warm-up: arrays, 2ptr, sliding, BS + easy DP + easy graph | No HLD/LLD | D2: 45-60 min | E2: Just show up daily and solve one | F2: 5+ days done; can solve easy/medium
A3: 2 | B3: Hard DSA first + HLD/LLD basics | C3: DP 1D/2D + Graphs (DFS, topo, BFS) + SD template, estimation, cache, DB + OOP, SOLID, patterns | D3: 100 min - 2 hrs | E3: One hard DSA + one HLD + one LLD concept | F3: DP/Graph not terrifying; SD template + SOLID memorized
A4: 3 | B4: More hard DSA + first full designs | C4: DP knapsack/string, Trees, BST, BS-on-answer + URL shortener, rate limiter + Parking lot, Cache LRU, Splitwise | D4: 2 hrs | E4: Hard DSA + complete designs | F4: 2 HLD and 3 LLD done from scratch
A5: 4 | B5: Remaining hard + deeper designs | C5: Sliding window hard, heap, monotonic stack, backtracking, greedy + feed, chat, file storage + elevator, booking, vending machine | D5: 2-2.5 hrs | E5: All hard patterns + all designs | F5: Full coverage DSA + HLD + LLD
A6: 5 | B6: Timed hard DSA + strengthen designs | C6: Timed DP/graphs/trees first + revise all HLD + snake & ladder, logger | D6: 2.5 hrs | E6: Timed hard problems + reproduce designs from memory | F6: Fast under pressure; designs reproducible
A7: 6 | B7: Final revision (hard → easy order) | C7: DP → Graphs → Trees → BS → rest + reproduce all HLD/LLD + behavioral | D7: 2-3 hrs | E7: No new topics; hard patterns first in revision | F7: Ready for Senior SDE interview

Sheet AI ML Topics
A1: Priority | B1: Topic | C1: Key Concepts to Know | D1: Common Interview Questions | E1: Status | F1: Confidence 1-5 | G1: Notes
A2: CRITICAL | B2: ML Fundamentals | C2: Bias-variance tradeoff, overfitting, underfitting, regularization (L1/L2), cross-validation, train/val/test split | D2: Why is your model overfitting? How do you fix it? Explain bias-variance tradeoff.
A3: CRITICAL | B3: Supervised Learning | C3: Linear regression, logistic regression, decision trees, random forests, gradient boosting (XGBoost, LightGBM), SVM | D3: When would you use random forest vs gradient boosting? Explain how a decision tree splits.
A4: CRITICAL | B4: Model Evaluation Metrics | C4: Precision, recall, F1, AUC-ROC, confusion matrix, log loss, MSE/MAE, R-squared | D4: Your model has 99% accuracy but fails in production. Why? When to optimize for recall vs precision?
A5: CRITICAL | B5: Deep Learning Basics | C5: Neural network architecture, backpropagation, activation functions (ReLU, sigmoid, softmax), optimizers (SGD, Adam), batch normalization, dropout | D5: Walk through backpropagation. Why ReLU over sigmoid? What does batch norm do?
A6: CRITICAL | B6: Transformers & Attention | C6: Self-attention mechanism, multi-head attention, positional encoding, encoder-decoder architecture, BERT vs GPT | D6: Explain self-attention. Why do transformers outperform RNNs? What is positional encoding for?
A7: CRITICAL | B7: LLMs & GenAI | C7: GPT architecture, tokenization (BPE), temperature/top-p, prompt engineering, fine-tuning (LoRA, QLoRA), RLHF, hallucination, context window | D7: How does GPT generate text? What causes hallucination? How would you reduce it? Explain RLHF.
A8: CRITICAL | B8: RAG (Retrieval Augmented Generation) | C8: Embedding models, vector databases, chunking strategies, retrieval pipeline, re-ranking, hybrid search, evaluation (faithfulness, relevance) | D8: Design a RAG system. How do you evaluate retrieval quality? When RAG vs fine-tuning?
A9: CRITICAL | B9: Feature Engineering | C9: Feature selection, scaling (standard/minmax), encoding (one-hot, target, label), handling missing values, feature importance, feature stores | D9: How do you handle categorical features with 10K categories? How do you detect important features?
A10: HIGH | B10: ML System Design | C10: Model serving (batch vs real-time), A/B testing, feature stores, model monitoring, data pipelines, latency vs throughput | D10: Design a recommendation system. How do you serve a model at 10K QPS? How do you detect model drift?
A11: HIGH | B11: Embeddings & Vector Search | C11: Word2Vec, sentence embeddings, cosine similarity, ANN (HNSW, IVF), vector databases (Pinecone, Weaviate, pgvector), dimensionality | D11: How does cosine similarity work? How do you choose embedding dimension? ANN vs exact search tradeoffs?
A12: HIGH | B12: NLP Fundamentals | C12: Tokenization, TF-IDF, word embeddings, named entity recognition, text classification, sentiment analysis, sequence labeling | D12: How would you build a text classifier? What is the difference between TF-IDF and embeddings?
A13: HIGH | B13: MLOps & Production ML | C13: CI/CD for ML, model versioning, experiment tracking, drift detection, retraining pipelines, monitoring (data drift, concept drift), shadow deployment | D13: How do you know when to retrain? What metrics do you monitor in production? How do you rollback a bad model?
... A26: GOOD TO KNOW | B26: Ethics & Safety | C26: Bias in models, fairness metrics, responsible AI, alignment, red teaming, content filtering | D26: How do you detect bias? What guardrails would you add to an LLM product?

Sheet Data Engineering Topics
A1: Priority | B1: Topic | C1: Key Concepts to Know | D1: Common Interview Questions | E1: Status | F1: Confidence 1-5 | G1: Notes
A2: CRITICAL | B2: SQL (Advanced) | C2: Window functions (ROW_NUMBER, RANK, LAG, LEAD), CTEs, recursive queries, joins (all types), subqueries, query optimization, execution plans, indexing strategies | D2: Write a query for running totals. Find duplicates. Optimize a slow query. Explain execution plan.
A3: CRITICAL | B3: Data Modeling | C3: Star schema, snowflake schema, normalized vs denormalized, slowly changing dimensions (SCD types), fact vs dimension tables, data vault, wide tables | D3: Design a data model for an e-commerce system. When to denormalize? Explain SCD Type 2.
A4: CRITICAL | B4: ETL / ELT Pipelines | C4: Extract-Transform-Load vs ELT, batch vs streaming, idempotency, backfilling, schema evolution, data quality checks, pipeline orchestration | D4: Design a pipeline for daily sales aggregation. How do you handle late-arriving data? How do you ensure idempotency?
A5: CRITICAL | B5: Apache Spark | C5: RDDs, DataFrames, transformations vs actions, lazy evaluation, partitioning, shuffles, broadcast joins, caching, Spark SQL, UDFs, memory management | D5: Why is your Spark job slow? Explain shuffle. When to broadcast? How do you handle data skew?
A6: CRITICAL | B6: Data Warehousing | C6: OLAP vs OLTP, columnar storage, partitioning, clustering, materialized views, query engines (BigQuery, Redshift, Snowflake, Databricks) | D6: OLAP vs OLTP differences. Why columnar for analytics? How does partitioning improve performance?
A7: CRITICAL | B7: Batch vs Stream Processing | C7: Batch (Spark, Airflow), streaming (Kafka, Flink, Spark Streaming), exactly-once vs at-least-once, windowing (tumbling, sliding, session), watermarks, late data | D7: When batch vs streaming? Explain exactly-once semantics. How do you handle out-of-order events?
A8: HIGH | B8: Apache Kafka | C8: Topics, partitions, consumer groups, offsets, producers, replication, retention, compaction, Schema Registry, Kafka Connect, exactly-once delivery | D8: Design event streaming for order processing. How does Kafka guarantee ordering? What happens when a consumer falls behind?
A9: HIGH | B9: Orchestration (Airflow) | C9: DAGs, tasks, operators, sensors, XComs, scheduling, retries, backfill, task dependencies, dynamic DAGs, Airflow vs Dagster vs Prefect | D9: Design a DAG for daily ETL. How do you handle task failures? How do you backfill 30 days?
A10: HIGH | B10: Data Quality & Testing | C10: Data validation (Great Expectations, dbt tests), schema checks, freshness checks, null/duplicate detection, data contracts, observability, lineage | D10: How do you catch bad data before it reaches dashboards? What data quality checks do you run?
A11: HIGH | B11: Distributed Systems for DE | C11: CAP theorem, eventual consistency, partitioning strategies, replication, distributed file systems (HDFS, S3), data locality | D11: Explain CAP theorem for data systems. How does HDFS store data? Why is data locality important for Spark?
A12: HIGH | B12: dbt & Transformation Layer | C12: Models, materializations (table, view, incremental), tests, documentation, sources, refs, Jinja macros, dbt Cloud vs Core | D12: How does incremental materialization work? When table vs view? How do you test transformations?
A13: HIGH | B13: File Formats & Storage | C13: Parquet, ORC, Avro, JSON, CSV tradeoffs, columnar vs row, compression (Snappy, Gzip, Zstd), partitioned storage, Delta Lake, Iceberg, Hudi | D13: Why Parquet over CSV? Explain columnar advantage. What is Delta Lake / Iceberg and why use it?
... A24: GOOD TO KNOW | B24: ML Pipelines for DE | C24: Feature stores, training data pipelines, model input/output schemas, feature freshness, offline vs online features | D24: Design a feature pipeline for a recommendation model. How do you ensure feature freshness?

Sheet DSA Mistake Log
A1: Date | B1: Problem | C1: Platform | D1: Difficulty | E1: Pattern | F1: Mistake Type | G1: Root Cause | H1: Wrong Approach | I1: Correct Insight | J1: Edge Case Missed | K1: Time Lost Min | L1: Re-solve Date | M1: Re-solve Status | N1: Final Confidence 1-5 | O1: Notes

Sheet System Design Mistakes
A1: Date | B1: Design Problem | C1: Mistake Area | D1: What Went Wrong | E1: Better Answer | F1: Trade-off Missed | G1: Scale/Numbers Gap | H1: Failure Mode Missed | I1: Follow-up Resource | J1: Review Date | K1: Confidence 1-5

Sheet LLD Mistakes
A1: Date | B1: Problem | C1: Mistake Area | D1: Bad Design Symptom | E1: Better Design | F1: Pattern/Principle | G1: Class/Interface To Improve | H1: Test Case Missed | I1: Review Date | J1: Confidence 1-5

Sheet Mock Interviews
A1: Date | B1: Round Type | C1: Interviewer/Source | D1: Problem/Topic | E1: Result | F1: Score 1-5 | G1: Strong Points | H1: Weak Points | I1: Top Correction | J1: Communication Score 1-5 | K1: Technical Score 1-5 | L1: Next Action | M1: Done

Sheet Weekly Review
A1: Week | B1: Start Date | C1: Daily Score Total | D1: DSA Solved | E1: DSA Re-solved | F1: System Designs | G1: LLD Problems | H1: Mocks | I1: Top Mistake 1 | J1: Top Mistake 2 | K1: Top Mistake 3 | L1: What Worked | M1: What Did Not Work | N1: One Change Next Week | O1: Readiness 1-5
A2: 1 | B2: 2026-08-25 | C2: =SUMPRODUCT(('Daily Tracker'!B2:B200=1)*('Daily Tracker'!N2:N200)) | D2: =COUNTIFS('Daily Tracker'!B2:B200,1,'Daily Tracker'!J2:J200,"<>")
A3: 2 | B3: 2026-09-01 | C3: =SUMPRODUCT(('Daily Tracker'!B2:B200=2)*('Daily Tracker'!N2:N200)) | D3: =COUNTIFS('Daily Tracker'!B2:B200,2,'Daily Tracker'!J2:J200,"<>")
A4: 3 | B4: 2026-09-08 | C4: =SUMPRODUCT(('Daily Tracker'!B2:B200=3)*('Daily Tracker'!N2:N200)) | D4: =COUNTIFS('Daily Tracker'!B2:B200,3,'Daily Tracker'!J2:J200,"<>")
A5: 4 | B5: 2026-09-15 | C5: =SUMPRODUCT(('Daily Tracker'!B2:B200=4)*('Daily Tracker'!N2:N200)) | D5: =COUNTIFS('Daily Tracker'!B2:B200,4,'Daily Tracker'!J2:J200,"<>")
A6: 5 | B6: 2026-09-22 | C6: =SUMPRODUCT(('Daily Tracker'!B2:B200=5)*('Daily Tracker'!N2:N200)) | D6: =COUNTIFS('Daily Tracker'!B2:B200,5,'Daily Tracker'!J2:J200,"<>")
A7: 6 | B7: 2026-09-29 | C7: =SUMPRODUCT(('Daily Tracker'!B2:B200=6)*('Daily Tracker'!N2:N200)) | D7: =COUNTIFS('Daily Tracker'!B2:B200,6,'Daily Tracker'!J2:J200,"<>")

Sheet Resume Stories
A1: Story | B1: Company/Project | C1: Situation | D1: Task | E1: Action | F1: Result | G1: Technical Depth | H1: Metrics | I1: Senior Signal | J1: Weak Gap | K1: Practiced Out Loud | L1: Confidence 1-5
A2: Most technically difficult project
A3: Project with measurable business impact
A4: Production bug or outage you resolved
A5: Performance or scalability improvement
A6: System you designed end-to-end
A7: Conflict or disagreement with teammate
A8: Time you showed ownership beyond your role
A9: Failure or mistake and what you learned
A10: Mentoring or leading without authority
A11: Why this company / why this role

Sheet Company Pipeline
A1: Company | B1: Role | C1: Level | D1: Source | E1: Status | F1: Applied Date | G1: Recruiter | H1: Next Round | I1: Next Date | J1: Prep Focus | K1: Notes | L1: Follow-up Date

Sheet Readiness Dashboard
A1: Metric | B1: Value | C1: Target | D1: Meaning
A2: Total prep days | B2: =COUNTIF('Daily Tracker'!N2:N200,">0") | C2: 30+ | D2: Days you actually showed up and scored
A3: Average daily score | B3: =IFERROR(AVERAGEIF('Daily Tracker'!N2:N200,">0"),"") | C3: 4+ | D3: Quality of consistency
A4: DSA mistakes logged | B4: =COUNTA('DSA Mistake Log'!B2:B500) | C4: 35+ | D4: Learning from errors
A5: DSA pending re-solves | B5: =COUNTIF('DSA Mistake Log'!M2:M500,"Pending") | C5: 0-8 | D5: Backlog before interview
A6: System design gaps logged | B6: =COUNTA('System Design Mistakes'!B2:B500) | C6: 10+ | D6: Trade-off awareness
A7: LLD gaps logged | B7: =COUNTA('LLD Mistakes'!B2:B500) | C7: 8+ | D7: Design modeling clarity
A8: Mocks completed | B8: =COUNTA('Mock Interviews'!B2:B500) | C8: 6+ | D8: Pressure practice
A9: Resume stories practiced | B9: =COUNTIF('Resume Stories'!K2:K200,"Yes") | C9: 6+ | D9: Behavioral confidence
A10: AI/ML topics confident | B10: =COUNTIF('AI ML Topics'!E2:E100,"Confident") | C10: 15+ | D10: ML topics you can explain clearly
A11: Data Engineering topics confident | B11: =COUNTIF('Data Engineering Topics'!E2:E100,"Confident") | C11: 12+ | D11: DE topics you can explain clearly

Sheet README
A1: Senior Software Engineer Interview Tracker
A2: Senior SDE interview tracker. Daily Tracker focuses on DSA + SDE depth (system design, backend, LLD). AI ML Topics and Data Engineering Topics sheets are for your ML/AI prep at your own pace — not forced daily. 6 weeks from 2026-08-25, building from light habit to full simulation.
A4: How to use daily
A5: 1. Fill one row in Daily Tracker every prep day.
A6: 2. Log every non-trivial DSA mistake in DSA Mistake Log.
A7: 3. Log design and LLD gaps separately; senior rounds punish vague trade-offs.
A8: 4. After mocks, capture feedback in Mock Interviews within 10 minutes.
A9: 5. Every Sunday, complete Weekly Review and choose one adjustment for next week.
A12: Scoring guide
A13: 5 = plan completed plus mistake review
A14: 4 = daily minimum completed
A15: 3 = partial but meaningful effort
... A31: Covers all DE interview topics ordered by frequency: CRITICAL (SQL advanced, data modeling, ETL/ELT, Spark, warehousing, batch vs stream), HIGH (Kafka, Airflow, data quality, distributed systems, dbt, file formats, data lake), MEDIUM (Python for DE, cloud services, CDC, governance, Kimball, performance), GOOD TO KNOW (real-time analytics, data mesh, NoSQL/graph, ML pipelines for DE).
